MANIFEST.in
README.rst
setup.cfg
setup.py
src/cr/vision/__init__.py
src/cr/vision/array.py
src/cr/vision/errors.py
src/cr/vision/matrix.py
src/cr/vision/setup.py
src/cr/vision/vector.py
src/cr/vision/apps/__init__.py
src/cr/vision/apps/capture.py
src/cr/vision/apps/ipcam.py
src/cr/vision/concurrent/__init__.py
src/cr/vision/concurrent/base.py
src/cr/vision/concurrent/graph.py
src/cr/vision/concurrent/motion_detection.py
src/cr/vision/concurrent/on_screen_display.py
src/cr/vision/concurrent/video_stream.py
src/cr/vision/concurrent/webcam_stream.py
src/cr/vision/core/__init__.py
src/cr/vision/core/bb.py
src/cr/vision/core/colors.py
src/cr/vision/core/contour.py
src/cr/vision/core/cvt_color.py
src/cr/vision/core/effects.py
src/cr/vision/core/histogram.py
src/cr/vision/core/misc.py
src/cr/vision/core/noise_gaussian.py
src/cr/vision/core/noise_snp.py
src/cr/vision/core/opencv.py
src/cr/vision/core/operations.py
src/cr/vision/core/plot.py
src/cr/vision/core/scaling.py
src/cr/vision/core/template.py
src/cr/vision/core/threshold.py
src/cr/vision/core/types.py
src/cr/vision/crx/__init__.py
src/cr/vision/crx/components.py
src/cr/vision/crx/player.py
src/cr/vision/crx/webcam.py
src/cr/vision/edits/__init__.py
src/cr/vision/edits/animation.py
src/cr/vision/edits/border.py
src/cr/vision/edits/logo.py
src/cr/vision/edits/placement.py
src/cr/vision/faces/__init__.py
src/cr/vision/faces/cascade.py
src/cr/vision/filters/__init__.py
src/cr/vision/filters/filter.py
src/cr/vision/filters/kernels.py
src/cr/vision/geom/__init__.py
src/cr/vision/geom/projective2d_actions.py
src/cr/vision/geom/projective2d_matrices.py
src/cr/vision/io/__init__.py
src/cr/vision/io/display.py
src/cr/vision/io/interfaces.py
src/cr/vision/io/videocapture.py
src/cr/vision/io/videowriter.py
src/cr/vision/measure/__init__.py
src/cr/vision/measure/focus.py
src/cr/vision/motion/__init__.py
src/cr/vision/motion/simple_motion_detector.py
src/cr/vision/object_detection/__init__.py
src/cr_vision.egg-info/PKG-INFO
src/cr_vision.egg-info/SOURCES.txt
src/cr_vision.egg-info/dependency_links.txt
src/cr_vision.egg-info/entry_points.txt
src/cr_vision.egg-info/not-zip-safe
src/cr_vision.egg-info/requires.txt
src/cr_vision.egg-info/top_level.txt