Metadata-Version: 2.1
Name: cr-vision
Version: 0.1.0
Summary: Tools for Computer Vision
Home-page: UNKNOWN
Author: Carnot Research Pvt. Ltd.
Author-email: contact@carnotresearch.com
License: Apache 2.0: http://www.apache.org/licenses/LICENSE-2.0
Download-URL: https://github.com/carnotresearch/cr-vision/archive/v0.1.tar.gz
Project-URL: Issue Tracker, https://github.com/carnotresearch/cr-vision/issues
Keywords: Computer Vision
Platform: UNKNOWN
Classifier: Development Status :: 3 - Alpha
Classifier: Intended Audience :: Developers
Classifier: Topic :: Multimedia
Classifier: Topic :: Multimedia :: Video
Classifier: Topic :: Scientific/Engineering :: Image Processing
Classifier: Topic :: Scientific/Engineering :: Image Recognition
Classifier: License :: OSI Approved :: Apache Software License
Classifier: Operating System :: Unix
Classifier: Operating System :: POSIX
Classifier: Operating System :: Microsoft :: Windows
Classifier: Programming Language :: Python :: 3.7
Classifier: Programming Language :: Python :: 3.8
Classifier: Programming Language :: Python :: 3.9
Classifier: Programming Language :: Python :: Implementation :: CPython
Requires-Python: >=3.7
Provides-Extra: dev
Provides-Extra: test
